{
    "materials": {
        "gravel": [
            {
                "id": "7296932046",
                "name": "Gravel",
                "url": "https://sfbay.craigslist.org/pen/mat/d/los-altos-gravel/7296932046.html",
                "datetime": "2021-04-23 03:21",
                "price": "$0",
                "where": "los altos",
                "deleted": false,
                "image_url": "https://images.craigslist.org/00M0M_koZDXU3Teek_0hq0ne_600x450.jpg",
                "query": "gravel",
                "category": "maa"
            }
        ],
        "wood": [
            {
                "id": "7313834735",
                "name": "REDWOOD & DOUG FIR 3x10\" LONG LENGTHS WOOD",
                "url": "https://sfbay.craigslist.org/pen/mat/d/san-carlos-redwood-doug-fir-3x10-long/7313834735.html",
                "datetime": "2021-04-28 08:27",
                "price": "$7",
                "where": "san carlos",
                "deleted": false,
                "image_url": "https://images.craigslist.org/00U0U_aGQRntL72hvz_0ak07K_600x450.jpg",
                "query": "wood",
                "category": "maa"
            },
            {
                "id": "7309192339",
                "name": "4\u201dx13\u201d Douglas Fir Wood boards - partial painted 11 ft lengths",
                "url": "https://sfbay.craigslist.org/pen/mat/d/san-carlos-4x13-douglas-fir-wood-boards/7309192339.html",
                "datetime": "2021-04-28 08:09",
                "price": "$75",
                "where": "san carlos",
                "deleted": false,
                "image_url": "https://images.craigslist.org/00u0u_biUNlz31PScz_0ak08g_600x450.jpg",
                "query": "wood",
                "category": "maa"
            },
            {
                "id": "7313820714",
                "name": "Vintage Wood Window screens",
                "url": "https://sfbay.craigslist.org/pen/mat/d/san-carlos-vintage-wood-window-screens/7313820714.html",
                "datetime": "2021-04-28 08:04",
                "price": "$125",
                "where": "san carlos",
                "deleted": false,
                "image_url": "https://images.craigslist.org/00R0R_5O2tHbCcA4S_0gw0kE_600x450.jpg",
                "query": "wood",
                "category": "maa"
            }
        ]
    },
    "clothes": {
        "vintage": [
            {
                "id": "7313834418",
                "name": "Vintage Made In Italy Leather Striped Top Handle Bag / Brown Orange",
                "url": "https://sfbay.craigslist.org/eby/clo/d/oakland-vintage-made-in-italy-leather/7313834418.html",
                "datetime": "2021-04-28 08:26",
                "price": "$70",
                "where": "oakland lake merritt / grand",
                "deleted": false,
                "image_url": "https://images.craigslist.org/00f0f_233IwewtqTSz_0lM0t2_600x450.jpg",
                "query": "vintage",
                "category": "cla"
            },
            {
                "id": "7310346291",
                "name": "Vintage Mark Cross Ostrich Leather Handbag with Original Coin Purse",
                "url": "https://sfbay.craigslist.org/sfc/clo/d/vintage-mark-cross-ostrich-leather/7310346291.html",
                "datetime": "2021-04-28 08:12",
                "price": "$4,500",
                "where": "nob hill",
                "deleted": false,
                "image_url": "https://images.craigslist.org/01717_fegKs79GWRZ_600x450.jpg",
                "query": "vintage",
                "category": "cla"
            },
            {
                "id": "7311779594",
                "name": "VINTAGE LOOK RED PURSE WITH RHINESTONE X BY SASHA",
                "url": "https://sfbay.craigslist.org/sby/clo/d/vintage-look-red-purse-with-rhinestone/7311779594.html",
                "datetime": "2021-04-28 08:14",
                "price": "$20",
                "where": "san jose south",
                "deleted": false,
                "image_url": "https://images.craigslist.org/00V0V_4joQaBsnr8Z_600x450.jpg",
                "query": "vintage",
                "category": "cla"
            }
        ],
        "beaded": [
            {
                "id": "7313715581",
                "name": "* Set of 10 Designer Beaded Bracelets (by Roxanne Assoulin) *",
                "url": "https://sfbay.craigslist.org/eby/clo/d/emeryville-set-of-10-designer-beaded/7313715581.html",
                "datetime": "2021-04-27 23:47",
                "price": "$20",
                "where": "emeryville",
                "deleted": false,
                "image_url": "https://images.craigslist.org/00a0a_gR22uGJwXjvz_0ak07K_600x450.jpg",
                "query": "beaded",
                "category": "cla"
            },
            {
                "id": "7312636058",
                "name": "Beaded Drama Sleeveless Dress",
                "url": "https://sfbay.craigslist.org/nby/clo/d/napa-beaded-drama-sleeveless-dress/7312636058.html",
                "datetime": "2021-04-27 21:50",
                "price": "$10",
                "where": "napa county",
                "deleted": false,
                "image_url": "https://images.craigslist.org/00d0d_ig9QfqoUL69z_0dY0t2_600x450.jpg",
                "query": "beaded",
                "category": "cla"
            },
            {
                "id": "7313603800",
                "name": "Beautiful Brilliant Turquoise Blue Beaded Stringed Chunky Bracelet",
                "url": "https://sfbay.craigslist.org/eby/clo/d/alameda-beautiful-brilliant-turquoise/7313603800.html",
                "datetime": "2021-04-27 16:21",
                "price": "$30",
                "where": "alameda",
                "deleted": false,
                "image_url": "https://images.craigslist.org/00T0T_9qWub8Ru9Hr_0qu0t2_600x450.jpg",
                "query": "beaded",
                "category": "cla"
            }
        ],
        "gloves": [
            {
                "id": "7307561944",
                "name": "Fishnet 80's Wrist GLOVES White Rave School Spirit Cheerleader New!!!",
                "url": "https://sfbay.craigslist.org/eby/clo/d/martinez-fishnet-80s-wrist-gloves-white/7307561944.html",
                "datetime": "2021-04-28 07:44",
                "price": "$5",
                "where": "concord / pleasant hill / martinez",
                "deleted": false,
                "image_url": "https://images.craigslist.org/00Y0Y_ljaGfWceFIu_07K0ak_600x450.jpg",
                "query": "gloves",
                "category": "cla"
            },
            {
                "id": "7307520705",
                "name": "New Fishnet Gold GLoves Adult!",
                "url": "https://sfbay.craigslist.org/eby/clo/d/martinez-new-fishnet-gold-gloves-adult/7307520705.html",
                "datetime": "2021-04-28 07:38",
                "price": "$5",
                "where": "concord / pleasant hill / martinez",
                "deleted": false,
                "image_url": "https://images.craigslist.org/01414_e2EspyvF1Dv_07K0ak_600x450.jpg",
                "query": "gloves",
                "category": "cla"
            },
            {
                "id": "7313779994",
                "name": "Neon Pink Lace Gloves 80's Retro Fancy Dress Up Halloween Costume Acce",
                "url": "https://sfbay.craigslist.org/eby/clo/d/martinez-neon-pink-lace-gloves-80s/7313779994.html",
                "datetime": "2021-04-28 06:44",
                "price": "$5",
                "where": "concord / pleasant hill / martinez",
                "deleted": false,
                "image_url": "https://images.craigslist.org/00u0u_huQqoS16tYYz_07K0ak_600x450.jpg",
                "query": "gloves",
                "category": "cla"
            }
        ],
        "wedding dress": [
            {
                "id": "7309762081",
                "name": "JESSICA McCLINTOCK SIZE 4 STRAPLESS WEDDING DRESS BRAND NEW W/TAGS",
                "url": "https://sfbay.craigslist.org/sby/clo/d/jessica-mcclintock-size-strapless/7309762081.html",
                "datetime": "2021-04-28 08:08",
                "price": "$30",
                "where": "SAN JOSE",
                "deleted": false,
                "image_url": "https://images.craigslist.org/00505_h3AU6dsSrj0_600x450.jpg",
                "query": "wedding dress",
                "category": "cla"
            },
            {
                "id": "7309070506",
                "name": "Women\u2019s Maxi Dress Multi Way Wear Party Wedding Bridesmaid Knee Length, Red",
                "url": "https://sfbay.craigslist.org/pen/clo/d/san-mateo-womens-maxi-dress-multi-way/7309070506.html",
                "datetime": "2021-04-27 23:33",
                "price": "$10",
                "where": "San Mateo",
                "deleted": false,
                "image_url": "https://images.craigslist.org/00303_cpjLjb2HBL7z_0pO0CI_600x450.jpg",
                "query": "wedding dress",
                "category": "cla"
            },
            {
                "id": "7309070561",
                "name": "Women\u2019s Maxi Dress Multi Way Wear Party Wedding Bridesmaid Knee Length, Blac",
                "url": "https://sfbay.craigslist.org/pen/clo/d/san-mateo-womens-maxi-dress-multi-way/7309070561.html",
                "datetime": "2021-04-27 23:33",
                "price": "$10",
                "where": "San Mateo",
                "deleted": false,
                "image_url": "https://images.craigslist.org/01010_8zVEcq23Z7Qz_0pO0CI_600x450.jpg",
                "query": "wedding dress",
                "category": "cla"
            }
        ],
        "great condition": [
            {
                "id": "7309098061",
                "name": "Men's\\Women's Jackets- Great Condition- Lightweight & Comfy ($5-10 ea)",
                "url": "https://sfbay.craigslist.org/sby/clo/d/san-jose-menswomens-jackets-great/7309098061.html",
                "datetime": "2021-04-27 20:03",
                "price": "$5",
                "where": "san jose south",
                "deleted": false,
                "image_url": "https://images.craigslist.org/00O0O_17JNxo0fRKIz_0t20CI_600x450.jpg",
                "query": "great condition",
                "category": "cla"
            },
            {
                "id": "7313632891",
                "name": "vintage full length mink coat great condition",
                "url": "https://sfbay.craigslist.org/eby/clo/d/berkeley-vintage-full-length-mink-coat/7313632891.html",
                "datetime": "2021-04-27 17:33",
                "price": "$300",
                "where": "Berkeley",
                "deleted": false,
                "image_url": "https://images.craigslist.org/00k0k_tRulhNUuVqz_0CI0t2_600x450.jpg",
                "query": "great condition",
                "category": "cla"
            },
            {
                "id": "7311901137",
                "name": "AUTHENTIC COACH BLACK LEATHER HAND BAG - GREAT CONDITION",
                "url": "https://sfbay.craigslist.org/sby/clo/d/san-jose-authentic-coach-black-leather/7311901137.html",
                "datetime": "2021-04-27 08:57",
                "price": "$30",
                "where": "san jose east",
                "deleted": false,
                "image_url": "https://images.craigslist.org/00E0E_alQnTb2seNO_600x450.jpg",
                "query": "great condition",
                "category": "cla"
            }
        ]
    }
}
